<?xml version="1.0" ?><!DOCTYPE PubmedArticleSet PUBLIC "-//NLM//DTD PubMedArticle, 1st June 2018//EN" "https://dtd.nlm.nih.gov/ncbi/pubmed/out/pubmed_180601.dtd"><PubmedArticleSet><PubmedArticle>    <MedlineCitation Status="Publisher" Owner="NLM">        <PMID Version="1">30188400</PMID>        <DateRevised>            <Year>2018</Year>            <Month>09</Month>            <Day>13</Day>        </DateRevised>        <Article PubModel="Print-Electronic">            <Journal>                <ISSN IssnType="Electronic">1528-1140</ISSN>                <JournalIssue CitedMedium="Internet">                    <PubDate>                        <Year>2018</Year>                        <Month>Sep</Month>                        <Day>04</Day>                    </PubDate>                </JournalIssue>                <Title>Annals of surgery</Title>                <ISOAbbreviation>Ann. Surg.</ISOAbbreviation>            </Journal>            <ArticleTitle>A Comparative Analysis of Survival and Funding Discrepancies in Cancers with High Mortality.</ArticleTitle>            <ELocationID EIdType="doi" ValidYN="Y">10.1097/SLA.0000000000003042</ELocationID>            <Abstract>                <AbstractText Label="OBJECTIVE" NlmCategory="OBJECTIVE">Comparative analyses of survival and funding statistics in cancers with high mortality were performed to quantify discrepancies and identify areas for intervention.</AbstractText>                <AbstractText Label="BACKGROUND" NlmCategory="BACKGROUND">Discrepancies in research funding may contribute to stagnant survival rates in pancreatic ductal adenocarcinoma (PDAC).</AbstractText>                <AbstractText Label="METHODS" NlmCategory="METHODS">The Surveillance, Epidemiology, and End Results database was queried for survival statistics. Funding data were obtained from the National Cancer Institute (NCI). Clinical trial data were obtained from www.clinicaltrials.gov. Cancers with high mortality were included for analyses.</AbstractText>                <AbstractText Label="RESULTS" NlmCategory="RESULTS">Since 1997, PDAC has received lesser funding ($1.41 billion) than other cancers such as breast ($10.52 billion), prostate ($4.93 billion), lung ($4.80 billion), and colorectal ($4.50 billion). Similarly, fewer clinical trials have been completed in PDAC (n = 608) compared with breast (n = 1904), lung (n = 1629), colorectal (n = 1080), and prostate (n = 1055) cancer. Despite this, since 1997, dollars invested in PDAC research produced a greater return on investment with regards to 5-year overall survival (5Y-OS) compared with breast, prostate, uterine, and ovarian cancer. Incremental cost-effectiveness analysis demonstrates that millions (liver, non-Hodgkin lymphoma, and melanoma) and billions (colorectal and lung) of dollars were required for each additional 1% increase in 5Y-OS compared with PDAC. Funding of research towards early diagnosis of PDAC has decreased by 19% since 2007. For nearly all cancers, treatment-related research receives the highest percentage of NCI funding.</AbstractText>                <AbstractText Label="CONCLUSIONS" NlmCategory="CONCLUSIONS">Funding of PDAC research is significantly less than other cancers, despite its higher mortality and greater potential to improve 5Y-OS. Increased awareness and lobbying are required to increase funding, promote research, and improve survival.</AbstractText>            </Abstract>            <AuthorList CompleteYN="Y">                <Author ValidYN="Y">                    <LastName>Hall</LastName>                    <ForeName>Bradley R</ForeName>                    <Initials>BR</Initials>                    <AffiliationInfo>                        <Affiliation>Department of Surgery, Division of Surgical Oncology, University of Nebraska Medical Center, Omaha, NE.</Affiliation>                    </AffiliationInfo>                    <AffiliationInfo>                        <Affiliation>Department of Biochemistry and Molecular Biology, University of Nebraska Medical Center, Omaha, NE.</Affiliation>                    </AffiliationInfo>                </Author>                <Author ValidYN="Y">                    <LastName>Cannon</LastName>                    <ForeName>Andrew</ForeName>                    <Initials>A</Initials>                    <AffiliationInfo>                        <Affiliation>Department of Biochemistry and Molecular Biology, University of Nebraska Medical Center, Omaha, NE.</Affiliation>                    </AffiliationInfo>                </Author>                <Author ValidYN="Y">                    <LastName>Atri</LastName>                    <ForeName>Pranita</ForeName>                    <Initials>P</Initials>                    <AffiliationInfo>                        <Affiliation>Department of Biochemistry and Molecular Biology, University of Nebraska Medical Center, Omaha, NE.</Affiliation>                    </AffiliationInfo>                </Author>                <Author ValidYN="Y">                    <LastName>Wichman</LastName>                    <ForeName>Christopher S</ForeName>                    <Initials>CS</Initials>                    <AffiliationInfo>                        <Affiliation>College of Public Health, Department of Biostatistics, University of Nebraska Medical Center, Omaha, NE.</Affiliation>                    </AffiliationInfo>                </Author>                <Author ValidYN="Y">                    <LastName>Smith</LastName>                    <ForeName>Lynette M</ForeName>                    <Initials>LM</Initials>                    <AffiliationInfo>                        <Affiliation>College of Public Health, Department of Biostatistics, University of Nebraska Medical Center, Omaha, NE.</Affiliation>                    </AffiliationInfo>                </Author>                <Author ValidYN="Y">                    <LastName>Kumar</LastName>                    <ForeName>Sushil</ForeName>                    <Initials>S</Initials>                    <AffiliationInfo>                        <Affiliation>Department of Biochemistry and Molecular Biology, University of Nebraska Medical Center, Omaha, NE.</Affiliation>                    </AffiliationInfo>                </Author>                <Author ValidYN="Y">                    <LastName>Batra</LastName>                    <ForeName>Surinder K</ForeName>                    <Initials>SK</Initials>                    <AffiliationInfo>                        <Affiliation>Department of Biochemistry and Molecular Biology, University of Nebraska Medical Center, Omaha, NE.</Affiliation>                    </AffiliationInfo>                </Author>                <Author ValidYN="Y">                    <LastName>Wang</LastName>                    <ForeName>Hongmei</ForeName>                    <Initials>H</Initials>                    <AffiliationInfo>                        <Affiliation>College of Public Health, Department of Biostatistics, University of Nebraska Medical Center, Omaha, NE.</Affiliation>                    </AffiliationInfo>                </Author>                <Author ValidYN="Y">                    <LastName>Ganti</LastName>                    <ForeName>Apar Kishor</ForeName>                    <Initials>AK</Initials>                    <AffiliationInfo>                        <Affiliation>Department of Internal Medicine, Division of Hematology and Oncology, University of Nebraska Medical Center, Omaha, NE.</Affiliation>                    </AffiliationInfo>                    <AffiliationInfo>                        <Affiliation>Department of Internal Medicine, Division of Hematology and Oncology, VA Nebraska-Western Iowa Health Care System, Omaha, NE.</Affiliation>                    </AffiliationInfo>                </Author>                <Author ValidYN="Y">                    <LastName>Sasson</LastName>                    <ForeName>Aaron R</ForeName>                    <Initials>AR</Initials>                    <AffiliationInfo>                        <Affiliation>Department of Surgery, Division of Surgical Oncology, Stony Brook School of Medicine, Stony Brooke, NY.</Affiliation>                    </AffiliationInfo>                </Author>                <Author ValidYN="Y">                    <LastName>Are</LastName>                    <ForeName>Chandrakanth</ForeName>                    <Initials>C</Initials>                    <AffiliationInfo>                        <Affiliation>Department of Surgery, Division of Surgical Oncology, University of Nebraska Medical Center, Omaha, NE.</Affiliation>                    </AffiliationInfo>                </Author>            </AuthorList>            <Language>eng</Language>            <PublicationTypeList>                <PublicationType UI="D016428">Journal Article</PublicationType>            </PublicationTypeList>            <ArticleDate DateType="Electronic">                <Year>2018</Year>                <Month>09</Month>                <Day>04</Day>            </ArticleDate>        </Article>        <MedlineJournalInfo>            <Country>United States</Country>            <MedlineTA>Ann Surg</MedlineTA>            <NlmUniqueID>0372354</NlmUniqueID>            <ISSNLinking>0003-4932</ISSNLinking>        </MedlineJournalInfo>    </MedlineCitation>    <PubmedData>        <History>            <PubMedPubDate PubStatus="pubmed">                <Year>2018</Year>                <Month>9</Month>                <Day>7</Day>                <Hour>6</Hour>                <Minute>0</Minute>            </PubMedPubDate>            <PubMedPubDate PubStatus="medline">                <Year>2018</Year>                <Month>9</Month>                <Day>7</Day>                <Hour>6</Hour>                <Minute>0</Minute>            </PubMedPubDate>            <PubMedPubDate PubStatus="entrez">                <Year>2018</Year>                <Month>9</Month>                <Day>7</Day>                <Hour>6</Hour>                <Minute>0</Minute>            </PubMedPubDate>        </History>        <PublicationStatus>aheadofprint</PublicationStatus>        <ArticleIdList>            <ArticleId IdType="pubmed">30188400</ArticleId>            <ArticleId IdType="doi">10.1097/SLA.0000000000003042</ArticleId>        </ArticleIdList>    </PubmedData></PubmedArticle></PubmedArticleSet>