<?xml version="1.0" ?><!DOCTYPE PubmedArticleSet PUBLIC "-//NLM//DTD PubMedArticle, 1st June 2018//EN" "https://dtd.nlm.nih.gov/ncbi/pubmed/out/pubmed_180601.dtd"><PubmedArticleSet><PubmedArticle>    <MedlineCitation Status="In-Process" Owner="NLM">        <PMID Version="1">30187868</PMID>        <DateRevised>            <Year>2018</Year>            <Month>09</Month>            <Day>06</Day>        </DateRevised>        <Article PubModel="Print">            <Journal>                <ISSN IssnType="Print">1673-4254</ISSN>                <JournalIssue CitedMedium="Print">                    <Volume>38</Volume>                    <Issue>8</Issue>                    <PubDate>                        <Year>2018</Year>                        <Month>Jul</Month>                        <Day>30</Day>                    </PubDate>                </JournalIssue>                <Title>Nan fang yi ke da xue xue bao = Journal of Southern Medical University</Title>                <ISOAbbreviation>Nan Fang Yi Ke Da Xue Xue Bao</ISOAbbreviation>            </Journal>            <ArticleTitle>[Differences in expression profiles of circular RNA between luminal breast cancer cells and normal breast cells].</ArticleTitle>            <Pagination>                <MedlinePgn>1014-1019</MedlinePgn>            </Pagination>            <ELocationID EIdType="doi" ValidYN="Y">10.3969/j.issn.1673-4254.2018.08.19</ELocationID>            <Abstract>                <AbstractText Label="OBJECTIVE" NlmCategory="OBJECTIVE">To investigate the differences in the expression profiles of circular RNA (circRNA) between luminal breast cancer cells and normal breast cells.</AbstractText>                <AbstractText Label="METHODS" NlmCategory="METHODS">Total RNA extracted from luminal breast cancer cells MCF7 and normal breast cells MCF10A was digested with Rnase R to remove linear RNAs and enrich circRNAs. The enriched circRNAs were amplified and transcribed into fluorescent cRNAs using a random priming method, and were hybridized onto the circRNA hybridization array. The circRNA expression profiles of MCF7 and MCF10A cells were analyzed using Agilent Feature Extraction software. Quantile normalization and subsequent data processing were performed, and volcano plot filtering and hierarchical clustering were utilized to analyze the circRNA expression patterns. The expressions of 3 circRNAs with significant log fold changes were validated using qPCR.</AbstractText>                <AbstractText Label="RESULTS" NlmCategory="RESULTS">The hybridization array data revealed significant differences in the circRNA expression profiles between MCF7 and MCF10A cells. Compared with those of MCF10A cells, the 12910 circRNAs expressed in MCF7 cells showed 5964 up-regulated, 81 consistently regulated, and 6865 down-regulated circRNAs; 343 circRNAs showed a log fold change by more than 2 folds, among which 213 circRNAs were up-regulated and 130 were down-regulated. Nine circRNAs showed differential expressions by more than 2 folds, including 8 up-regulated ones, namely hsa_circRNA_061260 (6.02 folds), hsa_circRNA_103933 (5.96 folds), hsa_circRNA_005239 (5.84 folds), hsa_circRNA_100689 (5.69 folds), hsa_circRNA_004087 (5.60 folds), hsa_circRNA_104420 (5.25 folds), hsa_circRNA_104421 (5.13 folds) and hsa_circRNA_101222 (5.03 folds); only one circRNA was down-regulated, namely hsa_circRNA_104864 (5.09 folds). The expressions of hsa_circRNA_100689, hsa_circRNA_005239 and hsa_circRNA_104864 were further validated by qPCR, which yielded consistent results with the microarray data.</AbstractText>                <AbstractText Label="CONCLUSIONS" NlmCategory="CONCLUSIONS">The circRNA expression profiles differ significantly between luminal breast cancer cells and normal breast cells. These differentially expressed circRNAs may serve as potential novel targets for the diagnosis of luminal breast cancer.</AbstractText>            </Abstract>            <AuthorList CompleteYN="Y">                <Author ValidYN="Y">                    <LastName>Xiao</LastName>                    <ForeName>Bin</ForeName>                    <Initials>B</Initials>                    <AffiliationInfo>                        <Affiliation>Department of Laboratory Medicine, Guangzhou General Hospital of PLA, Guangzhou 510010, China.</Affiliation>                    </AffiliationInfo>                </Author>                <Author ValidYN="Y">                    <LastName>Wen</LastName>                    <ForeName>Jiaxin</ForeName>                    <Initials>J</Initials>                    <AffiliationInfo>                        <Affiliation>Department of Medical Laboratory, Nanfang Hospital, Southern Medical University, Guangzhou 501515, China.</Affiliation>                    </AffiliationInfo>                </Author>                <Author ValidYN="Y">                    <LastName>Zhao</LastName>                    <ForeName>Chaoran</ForeName>                    <Initials>C</Initials>                    <AffiliationInfo>                        <Affiliation>Department of Medical Laboratory, Nanfang Hospital, Southern Medical University, Guangzhou 501515, China.</Affiliation>                    </AffiliationInfo>                </Author>                <Author ValidYN="Y">                    <LastName>Chen</LastName>                    <ForeName>Lidan</ForeName>                    <Initials>L</Initials>                    <AffiliationInfo>                        <Affiliation>Department of Laboratory Medicine, Guangzhou General Hospital of PLA, Guangzhou 510010, China.</Affiliation>                    </AffiliationInfo>                </Author>                <Author ValidYN="Y">                    <LastName>Sun</LastName>                    <ForeName>Zhaohui</ForeName>                    <Initials>Z</Initials>                    <AffiliationInfo>                        <Affiliation>Department of Laboratory Medicine, Guangzhou General Hospital of PLA, Guangzhou 510010, China.</Affiliation>                    </AffiliationInfo>                </Author>                <Author ValidYN="Y">                    <LastName>Li</LastName>                    <ForeName>Linhai</ForeName>                    <Initials>L</Initials>                    <AffiliationInfo>                        <Affiliation>Department of Laboratory Medicine, Guangzhou General Hospital of PLA, Guangzhou 510010, China.</Affiliation>                    </AffiliationInfo>                </Author>            </AuthorList>            <Language>chi</Language>            <PublicationTypeList>                <PublicationType UI="D004740">English Abstract</PublicationType>                <PublicationType UI="D016428">Journal Article</PublicationType>            </PublicationTypeList>        </Article>        <MedlineJournalInfo>            <Country>China</Country>            <MedlineTA>Nan Fang Yi Ke Da Xue Xue Bao</MedlineTA>            <NlmUniqueID>101266132</NlmUniqueID>            <ISSNLinking>1673-4254</ISSNLinking>        </MedlineJournalInfo>        <KeywordList Owner="NOTNLM">            <Keyword MajorTopicYN="N">breast cancer</Keyword>            <Keyword MajorTopicYN="N">circRNA</Keyword>            <Keyword MajorTopicYN="N">expression profiles</Keyword>            <Keyword MajorTopicYN="N">luminal type</Keyword>        </KeywordList>    </MedlineCitation>    <PubmedData>        <History>            <PubMedPubDate PubStatus="entrez">                <Year>2018</Year>                <Month>9</Month>                <Day>7</Day>                <Hour>6</Hour>                <Minute>0</Minute>            </PubMedPubDate>            <PubMedPubDate PubStatus="pubmed">                <Year>2018</Year>                <Month>9</Month>                <Day>7</Day>                <Hour>6</Hour>                <Minute>0</Minute>            </PubMedPubDate>            <PubMedPubDate PubStatus="medline">                <Year>2018</Year>                <Month>9</Month>                <Day>7</Day>                <Hour>6</Hour>                <Minute>0</Minute>            </PubMedPubDate>        </History>        <PublicationStatus>ppublish</PublicationStatus>        <ArticleIdList>            <ArticleId IdType="pubmed">30187868</ArticleId>            <ArticleId IdType="doi">10.3969/j.issn.1673-4254.2018.08.19</ArticleId>        </ArticleIdList>    </PubmedData></PubmedArticle></PubmedArticleSet>